zope/app/folder/__init__.py
zope/app/folder/configure.zcml
zope/app/folder/filerepresentation.py
zope/app/folder/folder.py
zope/app/folder/interfaces.py
zope/app/folder/tests.py
zope/app/folder/browser/__init__.py
zope/app/folder/browser/configure.zcml
zope/app/folder/browser/folder_icon.gif
zope/app/folder/browser/preview.pt
zope_app_folder-6.0.dist-info/licenses/LICENSE.txt
zope_app_folder-6.0.dist-info/METADATA
zope_app_folder-6.0.dist-info/WHEEL
zope_app_folder-6.0.dist-info/top_level.txt
zope_app_folder-6.0.dist-info/RECORD
