Metadata-Version: 2.4
Name: zope.app.folder
Version: 6.0
Summary: Folder Content Type for Zope 3
Home-page: http://github.com/zopefoundation/zope.app.folder
Author: Zope Foundation and Contributors
Author-email: zope-dev@zope.dev
License: ZPL-2.1
Project-URL: Issue Tracker, https://github.com/zopefoundation/zope.app.folder/issues
Project-URL: Sources, https://github.com/zopefoundation/zope.app.folder
Keywords: zope3 folder site local component
Classifier: Development Status :: 5 - Production/Stable
Classifier: Environment :: Web Environment
Classifier: Intended Audience :: Developers
Classifier: License :: OSI Approved :: Zope Public License
Classifier: Programming Language :: Python
Classifier: Natural Language :: English
Classifier: Programming Language :: Python :: 3
Classifier: Programming Language :: Python :: 3.9
Classifier: Programming Language :: Python :: 3.10
Classifier: Programming Language :: Python :: 3.11
Classifier: Programming Language :: Python :: 3.12
Classifier: Programming Language :: Python :: 3.13
Classifier: Programming Language :: Python :: Implementation :: CPython
Classifier: Programming Language :: Python :: Implementation :: PyPy
Classifier: Operating System :: OS Independent
Classifier: Topic :: Internet :: WWW/HTTP
Classifier: Framework :: Zope :: 3
Requires-Python: >=3.9
License-File: LICENSE.txt
Requires-Dist: setuptools
Requires-Dist: zope.container
Requires-Dist: zope.site
Requires-Dist: zope.app.content>=4.0.0
Provides-Extra: test
Requires-Dist: zope.app.container; extra == "test"
Requires-Dist: zope.browsermenu; extra == "test"
Requires-Dist: zope.browserpage; extra == "test"
Requires-Dist: zope.browserresource; extra == "test"
Requires-Dist: zope.configuration; extra == "test"
Requires-Dist: zope.testing; extra == "test"
Requires-Dist: zope.testrunner>=6.4; extra == "test"
Provides-Extra: zcml
Requires-Dist: zope.app.container; extra == "zcml"
Requires-Dist: zope.browsermenu; extra == "zcml"
Requires-Dist: zope.browserpage; extra == "zcml"
Requires-Dist: zope.browserresource; extra == "zcml"
Dynamic: author
Dynamic: author-email
Dynamic: classifier
Dynamic: description
Dynamic: home-page
Dynamic: keywords
Dynamic: license
Dynamic: license-file
Dynamic: project-url
Dynamic: provides-extra
Dynamic: requires-dist
Dynamic: requires-python
Dynamic: summary
